sigils/__init__.py
sigils/__main__.py
sigils/benchmark.py
sigils/tests.py
sigils/tools.py
sigils-0.3.5.dist-info/LICENSE
sigils-0.3.5.dist-info/METADATA
sigils-0.3.5.dist-info/WHEEL
sigils-0.3.5.dist-info/entry_points.txt
sigils-0.3.5.dist-info/top_level.txt
sigils-0.3.5.dist-info/RECORD
