Metadata-Version: 2.1
Name: sigils
Version: 0.3.5
Summary: Interpolate %[meta-text] with %[sigils].
Author-email: Rafael Jesús Guillén Osorio <arthexis@gmail.com>
License: MIT
Project-URL: Source, https://github.com/arthexis/sigils
Project-URL: Bug-Tracker, https://github.com/arthexis/sigils/issues
Keywords: utils,sigils,string,text,meta-text,context
Classifier: Development Status :: 3 - Alpha
Classifier: Intended Audience :: Developers
Classifier: Topic :: Software Development :: Libraries
Classifier: Topic :: Text Processing :: Markup
Classifier: Topic :: Software Development :: Pre-processors
Classifier: Topic :: Internet :: WWW/HTTP :: Dynamic Content
Classifier: Environment :: Console
Classifier: License :: OSI Approved :: MIT License
Classifier: Programming Language :: Python :: 3
Classifier: Programming Language :: Python :: 3.9
Classifier: Programming Language :: Python :: 3.10
Classifier: Programming Language :: Python :: 3.11
Requires-Python: >=3.9
License-File: LICENSE
